easy_health_check/__init__.py
easy_health_check/middleware.py
easy_health_check/settings.py
django_easy_health_check-1.0.1.dist-info/METADATA
django_easy_health_check-1.0.1.dist-info/WHEEL
django_easy_health_check-1.0.1.dist-info/top_level.txt
django_easy_health_check-1.0.1.dist-info/RECORD
